MANIFEST.in
README.md
setup.py
refine_viaf/__init__.py
refine_viaf/tests.py
refine_viaf/views.py
refine_viaf.egg-info/PKG-INFO
refine_viaf.egg-info/SOURCES.txt
refine_viaf.egg-info/dependency_links.txt
refine_viaf.egg-info/requires.txt
refine_viaf.egg-info/top_level.txt