Metadata-Version: 1.1
Name: refine-viaf
Version: 0.4
Summary: VIAF Reconciliation Service for OpenRefine
Home-page: https://github.com/codeforkjeff/refine_viaf
Author: Jeff Chiu
Author-email: jeff@codefork.com
License: BSD License
Platform: UNKNOWN
Classifier: Development Status :: 4 - Beta
Classifier: Environment :: Web Environment
Classifier: Framework :: Django
Classifier: Intended Audience :: Developers
Classifier: Intended Audience :: Information Technology
Classifier: License :: OSI Approved :: BSD License
Classifier: Programming Language :: Python
Classifier: Topic :: Internet :: WWW/HTTP
